{
    "version": "1.5.0-beta.364",
    "description": "Cross-platform Apple Music client",
    "license": "AGPL-3.0-or-later",
    "homepage": "https://cider.sh",
    "architecture": {
        "64bit": {
            "url": "https://github.com/ciderapp/cider-releases/releases/download/v1.5.0-beta.364/Cider-Setup-winget-1.5.0-beta.364.exe#/dl.7z",
            "hash": "sha512:829776b3ede80c954ea5fd09cc4a2cba7e40b5c77f060d95ab90a6fbeb71b05dac98f4e721bd693dc546e5c5eaad6b50ac749134670e583f7a9db56b3129813a",
            "installer": {
                "script": "Expand-7zipArchive -Path \"$dir\\`$PLUGINSDIR\\app-64.7z\" \"$dir\""
            }
        }
    },
    "post_install": "Remove-Item \"$dir\\`$PLUGINSDIR\", \"$dir\\`$R0\" -Recurse -Force",
    "shortcuts": [
        [
            "Cider.exe",
            "Cider"
        ]
    ],
    "checkver": {
        "url": "https://github.com/ciderapp/cider-releases/releases",
        "regex": "Cider Version ([\\d\\.]+-beta\\.\\d+)"
    },
    "autoupdate": {
        "architecture": {
            "64bit": {
                "url": "https://github.com/ciderapp/cider-releases/releases/download/v$version/Cider-Setup-winget-$version.exe#/dl.7z",
                "hash": {
                    "url": "$baseurl/latest.yml",
                    "regex": "sha512:\\s+$base64"
                }
            }
        }
    }
}
