{
    "version": "1.4.7.2570",
    "description": "Cross-platform Apple Music client",
    "license": "AGPL-3.0-or-later",
    "homepage": "https://cider.sh",
    "architecture": {
        "64bit": {
            "url": "https://github.com/ciderapp/cider-releases/releases/download/v1.4.7.2570/Cider-Setup-winget-1.4.7-beta.exe#/dl.7z",
            "hash": "sha512:3fee4e9f7dfa42110aa0cf47186d7a1a37c71d7e8d5b6ed008b726a9f9bdc45a4ca14b060f4cb4d24022ca6f5c1cf09d6e0dfb6df4b656e51a46d7075f151dbe",
            "installer": {
                "script": "Expand-7zipArchive -Path \"$dir\\`$PLUGINSDIR\\app-64.7z\" \"$dir\""
            }
        }
    },
    "post_install": "Remove-Item \"$dir\\`$PLUGINSDIR\", \"$dir\\`$R0\" -Recurse -Force",
    "shortcuts": [
        [
            "Cider.exe",
            "Cider"
        ]
    ],
    "checkver": {
        "script": [
            "$url = 'https://api.github.com/repos/ciderapp/cider-releases/releases'",
            "$content = (Invoke-WebRequest $url).Content",
            "if (!($content -match 'Cider Version (?<stem>[\\d.]+) - Build (?<build>\\d+) \\(main\\)')) {",
            "   break",
            "}",
            "$vermatches = $matches",
            "Write-Output \"Version: $($vermatches.stem).$($vermatches.build) | Type: beta\""
        ],
        "regex": "Version: ((?<stem>[\\d\\.]{5})\\.(?<build>\\d+)) \\| Type: (?<type>.+)"
    },
    "autoupdate": {
        "architecture": {
            "64bit": {
                "url": "https://github.com/ciderapp/cider-releases/releases/download/v$version/Cider-Setup-winget-$matchStem-$matchType.exe#/dl.7z",
                "hash": {
                    "url": "$baseurl/latest.yml",
                    "regex": "sha512:\\s+$base64"
                }
            }
        }
    }
}
